.DS_Store
.gitignore
LICENSE.txt
README.rst
requirements.txt
setup.py
.github/workflows/tests.yml
docs/Makefile
docs/create_object_docs.py
docs/make.bat
docs/requirements.txt
docs/source/conf.py
docs/source/index.rst
docs/source/images/dsconverter.drawio
docs/source/images/dsconverter.png
docs/source/images/dspipeline.drawio
docs/source/images/dspipeline.png
docs/source/pages/cli_tools.rst
docs/source/pages/code_documentation.rst
docs/source/pages/config_options.rst
docs/source/pages/creating_tests.rst
docs/source/pages/design_overview.rst
docs/source/pages/inline_lessons.rst
docs/source/pages/solution_cells.rst
dscreate/__init__.py
dscreate/__main__.py
dscreate.egg-info/PKG-INFO
dscreate.egg-info/SOURCES.txt
dscreate.egg-info/dependency_links.txt
dscreate.egg-info/entry_points.txt
dscreate.egg-info/requires.txt
dscreate.egg-info/top_level.txt
dscreate/apps/BaseApp.py
dscreate/apps/ConfigApp.py
dscreate/apps/CreateApp.py
dscreate/apps/DsCreateApp.py
dscreate/apps/EditApp.py
dscreate/apps/GenerateApp.py
dscreate/apps/MarkdownApp.py
dscreate/apps/ShareApp.py
dscreate/apps/__init__.py
dscreate/compose/tests/BaseTest.py
dscreate/compose/tests/TestController.py
dscreate/compose/tests/TestGenerator.py
dscreate/compose/tests/__init__.py
dscreate/pipeline/CollectCurriculum.py
dscreate/pipeline/DsPipeline.py
dscreate/pipeline/__init__.py
dscreate/pipeline/controllers/BaseController.py
dscreate/pipeline/controllers/CheckoutController.py
dscreate/pipeline/controllers/CheckoutEditBranch.py
dscreate/pipeline/controllers/CommitController.py
dscreate/pipeline/controllers/PushController.py
dscreate/pipeline/controllers/__init__.py
dscreate/pipeline/converters/BaseConverter.py
dscreate/pipeline/converters/MasterConverter.py
dscreate/pipeline/converters/MergeConverter.py
dscreate/pipeline/converters/ReadmeConverter.py
dscreate/pipeline/converters/ReleaseConverter.py
dscreate/pipeline/converters/SolutionConverter.py
dscreate/pipeline/converters/SourceConverter.py
dscreate/pipeline/converters/__init__.py
dscreate/pipeline/preprocessors/AddCellIndex.py
dscreate/pipeline/preprocessors/AddLanguage.py
dscreate/pipeline/preprocessors/BasePreprocessor.py
