Metadata-Version: 1.0
Name: dscreate
Version: 0.2.0
Summary: Flatiron Iron School Data Science Tools
Home-page: http://github.com/learn-co-curriculum/dscreate
Author: Joel Collins
Author-email: joelsewhere@gmail.com
License: MIT
Platform: UNKNOWN
